kondunite.py
kondunite-0.1.14.dist-info/LICENSE
kondunite-0.1.14.dist-info/METADATA
kondunite-0.1.14.dist-info/WHEEL
kondunite-0.1.14.dist-info/entry_points.txt
kondunite-0.1.14.dist-info/top_level.txt
kondunite-0.1.14.dist-info/RECORD
