Metadata-Version: 2.1
Name: kondunite
Version: 0.1.14
Summary: Kubernetes Conditional Manifests Unifier
Home-page: https://github.com/ReallyLiri/kondunite
Author: ReallyLiri
Author-email: reallyliri@gmail.com
License: UNKNOWN
Keywords: k8s kubernetes kustomize yaml yml manifest gke repl replicated
Platform: UNKNOWN
Classifier: Programming Language :: Python :: 3
Classifier: Operating System :: OS Independent
Requires-Python: >=3.6
Requires-Dist: Click
Requires-Dist: ruamel.yaml
Requires-Dist: toposort
